att.py
setup.py
att.egg-info/PKG-INFO
att.egg-info/SOURCES.txt
att.egg-info/dependency_links.txt
att.egg-info/requires.txt
att.egg-info/top_level.txt