Metadata-Version: 1.1
Name: att
Version: 0.0.2
Summary: Extract informations from att website.
Home-page: https://github.com/alaingilbert/att
Author: Alain Gilbert
Author-email: alain.gilbert.15@gmail.com
License: MIT
Keywords: att
Platform: UNKNOWN
Classifier: Environment :: Console
Classifier: License :: OSI Approved :: MIT License
Classifier: Intended Audience :: Developers
Classifier: Natural Language :: English
Classifier: Operating System :: OS Independent
Classifier: Programming Language :: Python :: 2.6
Classifier: Programming Language :: Python :: 2.7
Classifier: Topic :: Utilities
